{
  "title": "Cutting-Edge Blockchain Innovations of 2024: How New Tech is Shaping the Future",
  "description": "Explore the latest blockchain innovations making waves in 2024, from cross-chain interoperability to Web3 privacy tools and CBDC advancements.",
  "date": "2024-10-30T00:00:00.000Z",
  "body": {
    "raw": "\n🌟 **Top Blockchain Innovations Shaping 2024**\n\nBlockchain technology continues to redefine industries in 2024 with groundbreaking advancements that push the boundaries of decentralized finance, digital security, and cross-chain compatibility. Here’s a look at the most promising blockchain developments of the year and what they mean for businesses, users, and the future of digital economies.\n\n<div className='mx-auto w-[300px] sm:w-[500px]'>\n    <img className='rounded-lg' src='/blockchain.png' />\n</div>\n\n### 🏦 **1. Central Bank Digital Currencies (CBDCs)**\n\nThe rise of **Central Bank Digital Currencies (CBDCs)** has taken the finance sector by storm in 2024. Major economies, including the European Union and several Asian countries, are fast-tracking their CBDC projects to modernize payment systems. CBDCs offer numerous advantages: faster transactions, reduced cash dependency, and the ability to make programmable payments (e.g., tax withholding at the time of transaction). Central banks see CBDCs as tools to increase financial inclusion, allowing users without traditional bank accounts to access government services directly through digital wallets.\n\nHowever, the implementation of CBDCs comes with regulatory and infrastructure challenges. According to a recent Financial Times analysis, CBDCs need robust compliance and security frameworks to maintain consumer trust and financial stability. This has made CBDCs both an exciting and complex evolution in blockchain application.\n\n### 🔐 **2. Enhanced Privacy Tools for Web3 and DeFi**\n\nPrivacy continues to be a priority for Web3 developers, and **Chainlink’s recent platform updates** are a prime example of how blockchain is enhancing data security. With new tools like the **Blockchain Privacy Manager** and **CCIP Private Transactions**, Chainlink enables confidential data handling across decentralized platforms. These tools help organizations maintain regulatory compliance by allowing data to be transferred securely across both public and private blockchains.\n\nThis is crucial for financial institutions and enterprises looking to enter the blockchain space while adhering to data privacy laws such as GDPR. The tools also support decentralized finance (DeFi) projects by protecting user data, a growing concern as DeFi becomes mainstream and users demand greater control over personal information.\n\n### 🔗 **3. Cross-Chain Interoperability for Seamless Transactions**\n\nThe year 2024 has seen substantial progress in **cross-chain interoperability**, driven by demand for multi-chain DeFi ecosystems. Projects like **Alchemy Pay** are launching scalable Layer-1 blockchains tailored for crypto and fiat payments, enabling smoother asset transfers between blockchain networks. With compatibility with the **Solana Virtual Machine (SVM)**, Alchemy’s chain bridges on-chain and off-chain transactions, making it easier for businesses to operate in both crypto and fiat environments. The goal is to enhance DeFi’s accessibility by supporting seamless transactions across different blockchains and platforms.\n\nBy addressing interoperability, these solutions make DeFi and other blockchain-based financial services more accessible, potentially driving mass adoption and more robust decentralized applications (DApps).\n\n<div className='mx-auto w-[300px] sm:w-[500px]'>\n    <img className='rounded-lg' src='https://cdn.pixabay.com/photo/2016/08/05/21/49/moog-1573329_1280.jpg' />\n</div>\n\n### 💸 **4. Institutional Support for Bitcoin and Ethereum ETFs**\n\nIn a groundbreaking move, the SEC recently approved options for **Bitcoin and Ethereum ETFs** listed on major exchanges like NYSE and CBOE. This decision is expected to boost liquidity, reduce volatility, and encourage more institutional investments in digital assets. ETFs make it easier for traditional investors to enter the crypto market, offering a regulated framework with protections against market manipulation. For the broader crypto ecosystem, this could mean a new wave of interest and capital influx from traditional finance sectors, creating more stability and trust in the market.\n\n### 🌐 **5. Digital Identity and Security with Blockchain**\n\nDigital identity solutions are gaining momentum as blockchain offers a decentralized and secure way to manage personal information. Projects backed by tech giants like **Microsoft** and **IBM** are building blockchain-based identity platforms that empower users to control their own data and verify their identity without relying on centralized databases. This is particularly transformative in sectors such as healthcare and finance, where privacy and data integrity are paramount.\n\nDecentralized identity solutions have applications beyond personal use; they can streamline business processes and reduce administrative costs by automating identity verification through blockchain. This trend in 2024 underscores the broader shift towards Web3, where users have greater control over their digital lives.\n\n### 🌱 **6. Sustainability and Energy-Efficient Blockchain Solutions**\n\nSustainability has become a key focus, particularly with the environmental impact of energy-intensive **Proof-of-Work (PoW)** consensus models like Bitcoin’s. To address this, blockchain platforms are moving towards more sustainable consensus mechanisms such as **Proof-of-Stake (PoS)**, which significantly reduces energy consumption. Ethereum’s transition to PoS in 2023 has already set the standard, encouraging other networks to adopt similar models.\n\nThis push toward greener blockchain technologies is in line with global environmental goals. Blockchain projects are also exploring ways to support carbon credit markets, providing transparent tracking of emissions and offsets. These initiatives show blockchain’s potential to contribute to sustainable development beyond digital finance.\n\n---\n\nThe developments in blockchain technology in 2024 reveal a dynamic landscape, one where privacy, interoperability, and sustainability are at the forefront of innovation. As new tools and frameworks continue to emerge, the blockchain space is poised to transform industries and redefine digital economies.\n\n**Sources:**\n- JD Supra on regulatory advancements in crypto ETFs and blockchain privacy tools.\n- Cryptonews on Alchemy Pay’s scalable blockchain for seamless transactions.\n- Financial Times on CBDCs and blockchain's role in global finance.\n",
    "code": "var Component=(()=>{var m=Object.create;var o=Object.defineProperty;var p=Object.getOwnPropertyDescriptor;var u=Object.getOwnPropertyNames;var g=Object.getPrototypeOf,y=Object.prototype.hasOwnProperty;var f=(i,e)=>()=>(e||i((e={exports:{}}).exports,e),e.exports),b=(i,e)=>{for(var a in e)o(i,a,{get:e[a],enumerable:!0})},s=(i,e,a,r)=>{if(e&&typeof e==\"object\"||typeof e==\"function\")for(let t of u(e))!y.call(i,t)&&t!==a&&o(i,t,{get:()=>e[t],enumerable:!(r=p(e,t))||r.enumerable});return i};var k=(i,e,a)=>(a=i!=null?m(g(i)):{},s(e||!i||!i.__esModule?o(a,\"default\",{value:i,enumerable:!0}):a,i)),v=i=>s(o({},\"__esModule\",{value:!0}),i);var l=f((x,c)=>{c.exports=_jsx_runtime});var C={};b(C,{default:()=>h,frontmatter:()=>w});var n=k(l()),w={title:\"Cutting-Edge Blockchain Innovations of 2024: How New Tech is Shaping the Future\",description:\"Explore the latest blockchain innovations making waves in 2024, from cross-chain interoperability to Web3 privacy tools and CBDC advancements.\",date:\"2024-10-30\"};function d(i){let e={h3:\"h3\",hr:\"hr\",li:\"li\",p:\"p\",strong:\"strong\",ul:\"ul\",...i.components};return(0,n.jsxs)(n.Fragment,{children:[(0,n.jsxs)(e.p,{children:[\"\\u{1F31F} \",(0,n.jsx)(e.strong,{children:\"Top Blockchain Innovations Shaping 2024\"})]}),`\n`,(0,n.jsx)(e.p,{children:\"Blockchain technology continues to redefine industries in 2024 with groundbreaking advancements that push the boundaries of decentralized finance, digital security, and cross-chain compatibility. Here\\u2019s a look at the most promising blockchain developments of the year and what they mean for businesses, users, and the future of digital economies.\"}),`\n`,(0,n.jsx)(\"div\",{className:\"mx-auto w-[300px] sm:w-[500px]\",children:(0,n.jsx)(\"img\",{className:\"rounded-lg\",src:\"/blockchain.png\"})}),`\n`,(0,n.jsxs)(e.h3,{children:[\"\\u{1F3E6} \",(0,n.jsx)(e.strong,{children:\"1. Central Bank Digital Currencies (CBDCs)\"})]}),`\n`,(0,n.jsxs)(e.p,{children:[\"The rise of \",(0,n.jsx)(e.strong,{children:\"Central Bank Digital Currencies (CBDCs)\"}),\" has taken the finance sector by storm in 2024. Major economies, including the European Union and several Asian countries, are fast-tracking their CBDC projects to modernize payment systems. CBDCs offer numerous advantages: faster transactions, reduced cash dependency, and the ability to make programmable payments (e.g., tax withholding at the time of transaction). Central banks see CBDCs as tools to increase financial inclusion, allowing users without traditional bank accounts to access government services directly through digital wallets.\"]}),`\n`,(0,n.jsx)(e.p,{children:\"However, the implementation of CBDCs comes with regulatory and infrastructure challenges. According to a recent Financial Times analysis, CBDCs need robust compliance and security frameworks to maintain consumer trust and financial stability. This has made CBDCs both an exciting and complex evolution in blockchain application.\"}),`\n`,(0,n.jsxs)(e.h3,{children:[\"\\u{1F510} \",(0,n.jsx)(e.strong,{children:\"2. Enhanced Privacy Tools for Web3 and DeFi\"})]}),`\n`,(0,n.jsxs)(e.p,{children:[\"Privacy continues to be a priority for Web3 developers, and \",(0,n.jsx)(e.strong,{children:\"Chainlink\\u2019s recent platform updates\"}),\" are a prime example of how blockchain is enhancing data security. With new tools like the \",(0,n.jsx)(e.strong,{children:\"Blockchain Privacy Manager\"}),\" and \",(0,n.jsx)(e.strong,{children:\"CCIP Private Transactions\"}),\", Chainlink enables confidential data handling across decentralized platforms. These tools help organizations maintain regulatory compliance by allowing data to be transferred securely across both public and private blockchains.\"]}),`\n`,(0,n.jsx)(e.p,{children:\"This is crucial for financial institutions and enterprises looking to enter the blockchain space while adhering to data privacy laws such as GDPR. The tools also support decentralized finance (DeFi) projects by protecting user data, a growing concern as DeFi becomes mainstream and users demand greater control over personal information.\"}),`\n`,(0,n.jsxs)(e.h3,{children:[\"\\u{1F517} \",(0,n.jsx)(e.strong,{children:\"3. Cross-Chain Interoperability for Seamless Transactions\"})]}),`\n`,(0,n.jsxs)(e.p,{children:[\"The year 2024 has seen substantial progress in \",(0,n.jsx)(e.strong,{children:\"cross-chain interoperability\"}),\", driven by demand for multi-chain DeFi ecosystems. Projects like \",(0,n.jsx)(e.strong,{children:\"Alchemy Pay\"}),\" are launching scalable Layer-1 blockchains tailored for crypto and fiat payments, enabling smoother asset transfers between blockchain networks. With compatibility with the \",(0,n.jsx)(e.strong,{children:\"Solana Virtual Machine (SVM)\"}),\", Alchemy\\u2019s chain bridges on-chain and off-chain transactions, making it easier for businesses to operate in both crypto and fiat environments. The goal is to enhance DeFi\\u2019s accessibility by supporting seamless transactions across different blockchains and platforms.\"]}),`\n`,(0,n.jsx)(e.p,{children:\"By addressing interoperability, these solutions make DeFi and other blockchain-based financial services more accessible, potentially driving mass adoption and more robust decentralized applications (DApps).\"}),`\n`,(0,n.jsx)(\"div\",{className:\"mx-auto w-[300px] sm:w-[500px]\",children:(0,n.jsx)(\"img\",{className:\"rounded-lg\",src:\"https://cdn.pixabay.com/photo/2016/08/05/21/49/moog-1573329_1280.jpg\"})}),`\n`,(0,n.jsxs)(e.h3,{children:[\"\\u{1F4B8} \",(0,n.jsx)(e.strong,{children:\"4. Institutional Support for Bitcoin and Ethereum ETFs\"})]}),`\n`,(0,n.jsxs)(e.p,{children:[\"In a groundbreaking move, the SEC recently approved options for \",(0,n.jsx)(e.strong,{children:\"Bitcoin and Ethereum ETFs\"}),\" listed on major exchanges like NYSE and CBOE. This decision is expected to boost liquidity, reduce volatility, and encourage more institutional investments in digital assets. ETFs make it easier for traditional investors to enter the crypto market, offering a regulated framework with protections against market manipulation. For the broader crypto ecosystem, this could mean a new wave of interest and capital influx from traditional finance sectors, creating more stability and trust in the market.\"]}),`\n`,(0,n.jsxs)(e.h3,{children:[\"\\u{1F310} \",(0,n.jsx)(e.strong,{children:\"5. Digital Identity and Security with Blockchain\"})]}),`\n`,(0,n.jsxs)(e.p,{children:[\"Digital identity solutions are gaining momentum as blockchain offers a decentralized and secure way to manage personal information. Projects backed by tech giants like \",(0,n.jsx)(e.strong,{children:\"Microsoft\"}),\" and \",(0,n.jsx)(e.strong,{children:\"IBM\"}),\" are building blockchain-based identity platforms that empower users to control their own data and verify their identity without relying on centralized databases. This is particularly transformative in sectors such as healthcare and finance, where privacy and data integrity are paramount.\"]}),`\n`,(0,n.jsx)(e.p,{children:\"Decentralized identity solutions have applications beyond personal use; they can streamline business processes and reduce administrative costs by automating identity verification through blockchain. This trend in 2024 underscores the broader shift towards Web3, where users have greater control over their digital lives.\"}),`\n`,(0,n.jsxs)(e.h3,{children:[\"\\u{1F331} \",(0,n.jsx)(e.strong,{children:\"6. Sustainability and Energy-Efficient Blockchain Solutions\"})]}),`\n`,(0,n.jsxs)(e.p,{children:[\"Sustainability has become a key focus, particularly with the environmental impact of energy-intensive \",(0,n.jsx)(e.strong,{children:\"Proof-of-Work (PoW)\"}),\" consensus models like Bitcoin\\u2019s. To address this, blockchain platforms are moving towards more sustainable consensus mechanisms such as \",(0,n.jsx)(e.strong,{children:\"Proof-of-Stake (PoS)\"}),\", which significantly reduces energy consumption. Ethereum\\u2019s transition to PoS in 2023 has already set the standard, encouraging other networks to adopt similar models.\"]}),`\n`,(0,n.jsx)(e.p,{children:\"This push toward greener blockchain technologies is in line with global environmental goals. Blockchain projects are also exploring ways to support carbon credit markets, providing transparent tracking of emissions and offsets. These initiatives show blockchain\\u2019s potential to contribute to sustainable development beyond digital finance.\"}),`\n`,(0,n.jsx)(e.hr,{}),`\n`,(0,n.jsx)(e.p,{children:\"The developments in blockchain technology in 2024 reveal a dynamic landscape, one where privacy, interoperability, and sustainability are at the forefront of innovation. As new tools and frameworks continue to emerge, the blockchain space is poised to transform industries and redefine digital economies.\"}),`\n`,(0,n.jsx)(e.p,{children:(0,n.jsx)(e.strong,{children:\"Sources:\"})}),`\n`,(0,n.jsxs)(e.ul,{children:[`\n`,(0,n.jsx)(e.li,{children:\"JD Supra on regulatory advancements in crypto ETFs and blockchain privacy tools.\"}),`\n`,(0,n.jsx)(e.li,{children:\"Cryptonews on Alchemy Pay\\u2019s scalable blockchain for seamless transactions.\"}),`\n`,(0,n.jsx)(e.li,{children:\"Financial Times on CBDCs and blockchain's role in global finance.\"}),`\n`]})]})}function h(i={}){let{wrapper:e}=i.components||{};return e?(0,n.jsx)(e,{...i,children:(0,n.jsx)(d,{...i})}):d(i)}return v(C);})();\n;return Component;"
  },
  "_id": "posts/cutting_edge_inovations.mdx",
  "_raw": {
    "sourceFilePath": "posts/cutting_edge_inovations.mdx",
    "sourceFileName": "cutting_edge_inovations.mdx",
    "sourceFileDir": "posts",
    "contentType": "mdx",
    "flattenedPath": "posts/cutting_edge_inovations"
  },
  "type": "Post",
  "slug": "/posts/cutting_edge_inovations",
  "slugAsParams": "cutting_edge_inovations"
}